aiotrans/__init__.py
aiotrans/cache/__init__.py
aiotrans/cache/cache.py
aiotrans/cache/storage/__init__.py
aiotrans/cache/storage/base.py
aiotrans/cache/storage/memory_storage.py
aiotrans/enums.py
aiotrans/translaitor.py
aiotrans/transport/__init__.py
aiotrans/transport/aiohttp_t.py
aiotrans/transport/base.py
aiotrans/transport/httpx_t.py
aiotrans/utils.py
aiotrans-1.2.dist-info/METADATA
aiotrans-1.2.dist-info/WHEEL
aiotrans-1.2.dist-info/RECORD
